pelican/plugins/pdf/__init__.py
pelican/plugins/pdf/pdf.py
pelican/plugins/pdf/test_pdf.py
pelican_pdf-1.0.5.dist-info/METADATA
pelican_pdf-1.0.5.dist-info/WHEEL
pelican_pdf-1.0.5.dist-info/licenses/LICENSE
pelican_pdf-1.0.5.dist-info/RECORD
