Metadata-Version: 2.1
Name: pelican-pdf
Version: 1.0.5
Summary: PDF Generator is a Pelican plugin that exports articles and pages as PDF files during site generation
Keywords: pelican,plugin,pdf,generator
Author-Email: Justin Mayer <entroP@gmail.com>, Dominik Wombacher <dominik@wombacher.cc>
License: AGPL-3.0
Classifier: Development Status :: 5 - Production/Stable
Classifier: Environment :: Console
Classifier: Framework :: Pelican
Classifier: Framework :: Pelican :: Plugins
Classifier: Intended Audience :: End Users/Desktop
Classifier: License :: OSI Approved :: GNU Affero General Public License v3
Classifier: Operating System :: OS Independent
Classifier: Programming Language :: Python :: 3
Classifier: Programming Language :: Python :: 3.8
Classifier: Programming Language :: Python :: 3.9
Classifier: Programming Language :: Python :: 3.10
Classifier: Programming Language :: Python :: 3.11
Classifier: Programming Language :: Python :: 3.12
Classifier: Topic :: Internet :: WWW/HTTP
Classifier: Topic :: Software Development :: Libraries :: Python Modules
Project-URL: Homepage, https://github.com/pelican-plugins/pdf
Project-URL: Issue tracker, https://github.com/pelican-plugins/pdf/issues
Project-URL: Funding, https://donate.getpelican.com/
Requires-Python: <4.0,>=3.8.1
Requires-Dist: pelican>=4.5
Requires-Dist: rst2pdf>=0.99
Requires-Dist: xhtml2pdf>=0.2.5
Requires-Dist: markdown>=3.4; extra == "markdown"
Provides-Extra: markdown
